microserver/__init__.py
microserver/__main__.py
microserver/glb.py
microserver/hookset.py
microserver/microserver.py
microserver/servers.py
microserver-1.0.8.dist-info/LICENSE
microserver-1.0.8.dist-info/METADATA
microserver-1.0.8.dist-info/NOTICE
microserver-1.0.8.dist-info/WHEEL
microserver-1.0.8.dist-info/entry_points.txt
microserver-1.0.8.dist-info/top_level.txt
microserver-1.0.8.dist-info/RECORD
